arena/__init__.py
arena/client.py
arena/models/__init__.py
arena/models/anthropic.py
arena/models/chat_completion.py
arena/models/evaluation.py
arena/models/mistral.py
arena/models/openai.py
arena/models/settings.py
arena_client-0.3.2.dist-info/METADATA
arena_client-0.3.2.dist-info/WHEEL
arena_client-0.3.2.dist-info/RECORD
